etx/__init__.py
etx/__main__.py
etx/summeriser.py
tests/Tests.py
tests/__init__.py
etx_sum-0.1.1.dist-info/LICENSE
etx_sum-0.1.1.dist-info/METADATA
etx_sum-0.1.1.dist-info/WHEEL
etx_sum-0.1.1.dist-info/entry_points.txt
etx_sum-0.1.1.dist-info/top_level.txt
etx_sum-0.1.1.dist-info/RECORD
