Metadata-Version: 2.1
Name: etx-sum
Version: 0.1.1
Summary: ext-sum.py is intended to be a small utillity script that gives a few greate stats on your daytrading results
Home-page: https://github.com/jesstruck/etx-summarizer
Author: Jes Struck
Author-email: mail@jesstruck.dk
License: UNKNOWN
Platform: UNKNOWN
Classifier: Programming Language :: Python :: 3
Classifier: License :: OSI Approved :: GNU General Public License v3 (GPLv3)
Classifier: Operating System :: OS Independent
Requires-Python: >=3.6
